odoo/addons/project_task_brand/README.rst
odoo/addons/project_task_brand/__init__.py
odoo/addons/project_task_brand/__manifest__.py
odoo/addons/project_task_brand/i18n/project_task_brand.pot
odoo/addons/project_task_brand/models/__init__.py
odoo/addons/project_task_brand/models/project_task.py
odoo/addons/project_task_brand/readme/CONTRIBUTORS.rst
odoo/addons/project_task_brand/readme/DESCRIPTION.rst
odoo/addons/project_task_brand/readme/USAGE.rst
odoo/addons/project_task_brand/static/description/icon.png
odoo/addons/project_task_brand/static/description/index.html
odoo/addons/project_task_brand/views/project_task.xml
odoo13_addon_project_task_brand-13.0.1.0.1.dev3.dist-info/METADATA
odoo13_addon_project_task_brand-13.0.1.0.1.dev3.dist-info/WHEEL
odoo13_addon_project_task_brand-13.0.1.0.1.dev3.dist-info/top_level.txt
odoo13_addon_project_task_brand-13.0.1.0.1.dev3.dist-info/RECORD
